pynamodb/__init__.py
pynamodb/_schema.py
pynamodb/_util.py
pynamodb/attributes.py
pynamodb/constants.py
pynamodb/exceptions.py
pynamodb/indexes.py
pynamodb/models.py
pynamodb/pagination.py
pynamodb/py.typed
pynamodb/settings.py
pynamodb/signals.py
pynamodb/transactions.py
pynamodb/types.py
pynamodb/connection/__init__.py
pynamodb/connection/_botocore_private.py
pynamodb/connection/base.py
pynamodb/connection/dax.py
pynamodb/connection/table.py
pynamodb/expressions/__init__.py
pynamodb/expressions/condition.py
pynamodb/expressions/operand.py
pynamodb/expressions/projection.py
pynamodb/expressions/update.py
pynamodb/expressions/util.py
tests/__init__.py
tests/data.py
tests/deep_eq.py
tests/response.py
tests/test_attributes.py
tests/test_base_connection.py
tests/test_binary_legacy_encoding.py
tests/test_discriminator.py
tests/test_exceptions.py
tests/test_expressions.py
tests/test_model.py
tests/test_pagination.py
tests/test_settings.py
tests/test_signals.py
tests/test_table_connection.py
tests/test_transaction.py
tests/integration/__init__.py
tests/integration/base_integration_test.py
tests/integration/binary_update_test.py
tests/integration/conftest.py
tests/integration/model_integration_test.py
tests/integration/table_integration_test.py
tests/integration/test_discriminator_index.py
tests/integration/test_transaction_integration.py
typing_tests/__init__.py
typing_tests/attributes.py
typing_tests/models.py
typing_tests/transactions.py
pynamodb_dax-0.0.6.dist-info/LICENSE
pynamodb_dax-0.0.6.dist-info/METADATA
pynamodb_dax-0.0.6.dist-info/WHEEL
pynamodb_dax-0.0.6.dist-info/top_level.txt
pynamodb_dax-0.0.6.dist-info/RECORD
